pjlog.py
pjlog-0.1.9.dist-info/LICENSE.txt
pjlog-0.1.9.dist-info/METADATA
pjlog-0.1.9.dist-info/WHEEL
pjlog-0.1.9.dist-info/top_level.txt
pjlog-0.1.9.dist-info/RECORD
