Metadata-Version: 2.1
Name: pjlog
Version: 0.1.9
Summary: Simple library for Logarithm with useful functions.
Home-page: https://github.com/immortal-zeus/pjlog
Author: Parsh Jain
Author-email: laspparshinc@gmail.com
License: UNKNOWN
Platform: UNKNOWN
Classifier: Programming Language :: Python :: Implementation :: PyPy
Classifier: Programming Language :: Python :: 3.7
Classifier: Programming Language :: Python :: 3.8
Classifier: Development Status :: 5 - Production/Stable
Classifier: License :: OSI Approved :: GNU General Public License v3 or later (GPLv3+)
Classifier: License :: Free For Educational Use
License-File: LICENSE.txt
Provides-Extra: dev
